<?xml version="1.0" encoding="UTF-8"?>
<root BTCPP_format="4"
      main_tree_to_execute="MainTree">
  <BehaviorTree ID="DoorClosed">
    <Fallback>
      <OpenDoor/>
      <RetryUntilSuccessful num_attempts="5">
        <PickLock/>
      </RetryUntilSuccessful>
      <SmashDoor/>
    </Fallback>
  </BehaviorTree>

  <BehaviorTree ID="MainTree">
    <Sequence>
      <Fallback>
        <Inverter>
          <IsDoorClosed/>
        </Inverter>
        <SubTree ID="DoorClosed"
                 _autoremap="false"/>
      </Fallback>
      <PassThroughDoor/>
    </Sequence>
  </BehaviorTree>

  <!-- Description of Node Models (used by Groot) -->
  <TreeNodesModel>
    <Condition ID="IsDoorClosed"
               editable="true"/>
    <Action ID="OpenDoor"
            editable="true"/>
    <Action ID="PassThroughDoor"
            editable="true"/>
    <Action ID="PickLock"
            editable="true"/>
    <Action ID="SmashDoor"
            editable="true"/>
  </TreeNodesModel>

</root>
